transphire/__init__.py
transphire/__main__.py
transphire/buttoncontainer.py
transphire/emaildialog.py
transphire/framecontainer.py
transphire/framewidget.py
transphire/inputbox.py
transphire/loadcontent.py
transphire/loadcontentcontainer.py
transphire/loadwindow.py
transphire/logviewer.py
transphire/logviewerdialog.py
transphire/mainwindow.py
transphire/messagebox.py
transphire/mountcalculator.py
transphire/mountcontainer.py
transphire/mountwidget.py
transphire/mountworker.py
transphire/notificationcontainer.py
transphire/notificationwidget.py
transphire/passworddialog.py
transphire/plotcontainer.py
transphire/plotwidget.py
transphire/plotworker.py
transphire/processthread.py
transphire/processworker.py
transphire/selectdialog.py
transphire/separator.py
transphire/settingscontainer.py
transphire/settingswidget.py
transphire/statuscontainer.py
transphire/statuswidget.py
transphire/tabdocker.py
transphire/templatedialog.py
transphire/testi.py
transphire/transphire_class2d.py
transphire/transphire_content.py
transphire/transphire_ctf.py
transphire/transphire_extract.py
transphire/transphire_import.py
transphire/transphire_motion.py
transphire/transphire_picking.py
transphire/transphire_plot.py
transphire/transphire_select2d.py
transphire/transphire_software.py
transphire/transphire_train2d.py
transphire/transphire_utils.py
transphire/images/Transphire.png
transphire/images/sxgui_background.png
transphire/support_scripts/__init__.py
transphire/support_scripts/chimerax.py
transphire/templates/cinderella_config.json
transphire-1.5.13.dist-info/LICENSE
transphire-1.5.13.dist-info/METADATA
transphire-1.5.13.dist-info/WHEEL
transphire-1.5.13.dist-info/entry_points.txt
transphire-1.5.13.dist-info/top_level.txt
transphire-1.5.13.dist-info/RECORD
