Metadata-Version: 2.1
Name: transphire
Version: 1.5.13
Summary: Automated post data aquisition processing tool
Home-page: https://github.com/mstabrin/transphire
Author: Markus Stabrin
Author-email: markus.stabrin@tu-dortmund.de
License: GPLv3
Platform: UNKNOWN
Classifier: Programming Language :: Python :: 3.6
Classifier: License :: OSI Approved :: GNU General Public License v3 or later (GPLv3+)
Classifier: Operating System :: POSIX :: Linux
Classifier: Environment :: X11 Applications :: Qt
Classifier: Development Status :: 4 - Beta
Requires-Dist: numpy
Requires-Dist: matplotlib
Requires-Dist: pexpect
Requires-Dist: cython
Requires-Dist: telepot
Requires-Dist: imageio
Requires-Dist: hyperspy
Requires-Dist: mrcfile
Requires-Dist: pandas
